{
  "resources": [
    {
      "path": "data.csv",
      "name": "data",
      "profile": "tabular-data-resource",
      "scheme": "file",
      "format": "csv",
      "hashing": "md5",
      "encoding": "utf-8",
      "schema": {
        "fields": [
          {
            "name": "Value",
            "type": "number"
          },
          {
            "name": "Year",
            "type": "integer"
          },
          {
            "name": "area",
            "type": "string",
            "constraints": {
              "enum": [
                "",
                "former federal territory",
                "germany",
                "new german states"
              ]
            }
          },
          {
            "name": "sex",
            "type": "string",
            "constraints": {
              "enum": [
                "",
                "female",
                "male"
              ]
            }
          }
        ]
      }
    }
  ],
  "profile": "data-package",
  "name": "2-1-2",
  "title": "Prävalenz von mittlerer oder schwerer Ernährungsunsicherheit in der Bevölkerung gemäß der Erfahrungsskala für Ernährungsunsicherheit (FIES)"
}